qmlearn/__init__.py
qmlearn/__main__.py
qmlearn/api/__init__.py
qmlearn/api/api4ase.py
qmlearn/api/constraints.py
qmlearn/cui/__init__.py
qmlearn/cui/traj2db.py
qmlearn/data/__init__.py
qmlearn/drivers/__init__.py
qmlearn/drivers/core.py
qmlearn/drivers/mol.py
qmlearn/drivers/psi4.py
qmlearn/drivers/pyscf.py
qmlearn/drivers/rotate.py
qmlearn/io/__init__.py
qmlearn/io/core.py
qmlearn/io/hdf5.py
qmlearn/io/model.py
qmlearn/model/__init__.py
qmlearn/model/build.py
qmlearn/model/model.py
qmlearn/preprocessing/__init__.py
qmlearn/preprocessing/vibrations.py
qmlearn/utils/__init__.py
qmlearn/utils/math.py
qmlearn/utils/utils.py
qmlearn/vibrations/__init__.py
qmlearn-0.0.1.dist-info/LICENSE
qmlearn-0.0.1.dist-info/METADATA
qmlearn-0.0.1.dist-info/WHEEL
qmlearn-0.0.1.dist-info/top_level.txt
qmlearn-0.0.1.dist-info/RECORD
